demo/__init__.py
demo/jwt/__init__.py
security_interface/__init__.py
security_interface/_version.py
security_interface/api.py
security_interface/exceptions.py
security_interface-0.1.0.dist-info/LICENSE
security_interface-0.1.0.dist-info/METADATA
security_interface-0.1.0.dist-info/WHEEL
security_interface-0.1.0.dist-info/top_level.txt
security_interface-0.1.0.dist-info/RECORD
