Metadata-Version: 2.1
Name: security-interface
Version: 0.1.0
Summary: Security Interface for you project.
Home-page: https://github.com/bruziev/security_interface
Author: Bakhtiyor Ruziev
Author-email: bakhtiyor.ruziev@yandex.ru
License: MIT
Platform: UNKNOWN
Classifier: Development Status :: 4 - Beta
Classifier: Intended Audience :: Developers
Classifier: License :: OSI Approved :: BSD License
Classifier: Programming Language :: Python
Classifier: Programming Language :: Python :: 3.6
